setup.py
HoleCardHandicapper.egg-info/PKG-INFO
HoleCardHandicapper.egg-info/SOURCES.txt
HoleCardHandicapper.egg-info/dependency_links.txt
HoleCardHandicapper.egg-info/requires.txt
HoleCardHandicapper.egg-info/top_level.txt
holecardhandicapper/__init__.py
holecardhandicapper/model/__init__.py
holecardhandicapper/model/const.py
holecardhandicapper/model/model_builder.py
holecardhandicapper/model/neuralnet.py
holecardhandicapper/model/utils.py
holecardhandicapper/model/data/preflop_winrate.csv
holecardhandicapper/model/weights/flop_cnn_model_weights.h5
holecardhandicapper/model/weights/preflop_neuralnet_model_weights.h5
holecardhandicapper/model/weights/river_cnn_model_weights.h5
holecardhandicapper/model/weights/turn_cnn_model_weights.h5