Metadata-Version: 1.1
Name: HoleCardHandicapper
Version: 1.1.0
Summary: NeuralNet for poker hands evaluation 
Home-page: https://github.com/ishikota/HoleCardHandicapper
Author: ishikota
Author-email: ishikota086@gmail.com
License: MIT
Keywords: python poker hand predict evaluate evaluator
Platform: UNKNOWN
Classifier: Development Status :: 5 - Production/Stable
Classifier: Topic :: Scientific/Engineering :: Artificial Intelligence
Classifier: License :: OSI Approved :: MIT License
